{
    "country": {

        "1": "Afghanistan",

        "2": "Albania",

        "3": "Algeria",

        "4": "American Samoa",

        "5": "Andorra",

        "6": "Angola",

        "7": "Anguilla",

        "8": "Antarctica",

        "9": "Antigua and Barbuda",

        "10": "Argentina",

        "11": "Armenia",

        "12": "Aruba",

        "13": "Australia",

        "14": "Austria",

        "15": "Azerbaijan",

        "16": "Bahamas",

        "17": "Bahrain",

        "18": "Bangladesh",

        "19": "Barbados",

        "20": "Belarus",

        "21": "Belgium",

        "22": "Belize",

        "23": "Benin",

        "24": "Bermuda",

        "25": "Bhutan",

        "26": "Bolivia",

        "27": "Bosnia and Herzegovina",

        "28": "Botswana",

        "29": "Brazil",

        "30": "British Indian Ocean Territory",

        "31": "British Virgin Islands",

        "32": "Brunei",

        "33": "Bulgaria",

        "34": "Burkina Faso",

        "35": "Burundi",

        "36": "Cambodia",

        "37": "Cameroon",

        "38": "Canada",

        "39": "Cape Verde",

        "40": "Cayman Islands",

        "41": "Central African Republic",

        "42": "Chad",

        "43": "Chile",

        "44": "China",

        "45": "Christmas Island",

        "46": "Cocos Islands",

        "47": "Colombia",

        "48": "Comoros",

        "49": "Cook Islands",

        "50": "Costa Rica",

        "51": "Croatia",

        "52": "Cuba",

        "53": "Curacao",

        "54": "Cyprus",

        "55": "Czech Republic",

        "56": "Democratic Republic of the Congo",

        "57": "Denmark",

        "58": "Djibouti",

        "59": "Dominica",

        "60": "Dominican Republic",

        "61": "East Timor",

        "62": "Ecuador",

        "63": "Egypt",

        "64": "El Salvador",

        "65": "Equatorial Guinea",

        "66": "Eritrea",

        "67": "Estonia",

        "68": "Ethiopia",

        "69": "Falkland Islands",

        "70": "Faroe Islands",

        "71": "Fiji",

        "72": "Finland",

        "73": "France",

        "74": "French Guiana",

        "75": "French polynesia",

        "76": "Gabon",

        "77": "Gambia",

        "78": "Georgia",

        "79": "Germany",

        "80": "Ghana",

        "81": "Gibraltar",

        "82": "Greece",

        "83": "Greenland",

        "84": "Grenada",

        "85": "Guam",

        "86": "Guatemala",

        "87": "Guernsey",

        "88": "Guinea",

        "89": "Guinea-Bissau",

        "90": "Guyana",

        "91": "Haiti",

        "92": "Honduras",

        "93": "Hong Kong",

        "94": "Hungary",

        "95": "Iceland",

        "96": "India",

        "97": "Indonesia",

        "98": "Iran",

        "99": "Iraq",

        "100": "Ireland",

        "101": "Isle of Man",

        "102": "Israel",

        "103": "Italy",

        "104": "Ivory Coast",

        "105": "Jamaica",

        "106": "Japan",

        "107": "Jersey",

        "108": "Jordan",

        "109": "Kazakhstan",

        "110": "Kenya",

        "111": "Kiribati",

        "112": "Kosovo",

        "113": "Kuwait",

        "114": "Kyrgyzstan",

        "115": "Laos",

        "116": "Latvia",

        "117": "Lebanon",

        "118": "Lesotho",

        "119": "Liberia",

        "120": "Libya",

        "121": "Liechtenstein",

        "122": "Lithuania",

        "123": "Luxembourg",

        "124": "Macao",

        "125": "Macedonia",

        "126": "Madagascar",

        "127": "Malawi",

        "128": "Malaysia",

        "129": "Maldives",

        "130": "Mali",

        "131": "Malta",

        "132": "Marshall Islands",

        "133": "Mauritania",

        "134": "Mauritius",

        "135": "Mayotte",

        "136": "Mexico",

        "137": "Micronesia",

        "138": "Moldova",

        "139": "Monaco",

        "140": "Mongolia",

        "141": "Montenegro",

        "142": "Montserrat",

        "143": "Morocco",

        "144": "Mozambique",

        "145": "Myanmar",

        "146": "Namibia",

        "147": "Nauru",

        "148": "Nepal",

        "149": "Netherlands",

        "150": "Netherlands Antilles",

        "151": "New Caledonia",

        "152": "New Zealand",

        "153": "Nicaragua",

        "154": "Niger",

        "155": "Nigeria",

        "156": "Niue",

        "157": "North Korea",

        "158": "Northern Mariana Islands",

        "159": "Norway",

        "160": "Oman",

        "161": "Pakistan",

        "162": "Palau",

        "163": "Palestine",

        "164": "Panama",

        "165": "Papua New Guinea",

        "166": "Paraguay",

        "167": "Peru",

        "168": "Philippines",

        "169": "Pitcairn",

        "170": "Poland",

        "171": "Portugal",

        "172": "Puerto Rico",

        "173": "Qatar",

        "174": "Republic of the Congo",

        "175": "Reunion",

        "176": "Romania",

        "177": "Russia",

        "178": "Rwanda",

        "179": "Saint Barthelemy",

        "180": "Saint Helena",

        "181": "Saint Kitts and Nevis",

        "182": "Saint Lucia",

        "183": "Saint Martin",

        "184": "Saint Pierre and Miquelon",

        "185": "Saint Vincent and the Grenadines",

        "186": "Samoa",

        "187": "San Marino",

        "188": "Sao Tome and Principe",

        "189": "Saudi Arabia",

        "190": "Senegal",

        "191": "Serbia",

        "192": "Seychelles",

        "193": "Sierra Leone",

        "194": "Singapore",

        "195": "Sint Maarten",

        "196": "Slovakia",

        "197": "Slovenia",

        "198": "Solomon Islands",

        "199": "Somalia",

        "200": "South Africa",

        "201": "South Korea",

        "202": "South Sudan",

        "203": "Spain",

        "204": "Sri Lanka",

        "205": "Sudan",

        "206": "Suriname",

        "207": "Svalbard and Jan Mayen",

        "208": "Swaziland",

        "209": "Sweden",

        "210": "Switzerland",

        "211": "Syria",

        "212": "Taiwan",

        "213": "Tajikistan",

        "214": "Tanzania",

        "215": "Thailand",

        "216": "Togo",

        "217": "Tokelau",

        "218": "Tonga",

        "219": "Trinidad and Tobago",

        "220": "Tunisia",

        "221": "Turkey",

        "222": "Turkmenistan",

        "223": "Turks and Caicos Islands",

        "224": "Tuvalu",

        "225": "U.S. Virgin Islands",

        "226": "Uganda",

        "227": "Ukraine",

        "228": "United Arab Emirates",

        "229": "United Kingdom",

        "230": "United States",

        "231": "Uruguay",

        "232": "Uzbekistan",

        "233": "Vanuatu",

        "234": "Vatican",

        "235": "Venezuela",

        "236": "Vietnam",

        "237": "Wallis and Futuna",

        "238": "Western Sahara",

        "239": "Yemen",

        "240": "Zambia",

        "241": "Zimbabwe"
    }
}